_bcj.pypy36-pp73-win32.pyd
bcj/__init__.py
bcj/__init__.pyi
bcj/py.typed
bcj_cffi-0.5.1.dist-info/LICENSE
bcj_cffi-0.5.1.dist-info/METADATA
bcj_cffi-0.5.1.dist-info/WHEEL
bcj_cffi-0.5.1.dist-info/top_level.txt
bcj_cffi-0.5.1.dist-info/RECORD
