Metadata-Version: 2.1
Name: bcj-cffi
Version: 0.5.1
Summary: bcj algorithm library
Home-page: http://github.com/miurahr/bcj-cffi
Author: Hiroshi Miura
Author-email: miurahr@linux.com
License: LGPL-2.1+
Keywords: 7zip,bcj
Platform: UNKNOWN
Classifier: Development Status :: 3 - Alpha
Classifier: License :: OSI Approved :: GNU Lesser General Public License v2 or later (LGPLv2+)
Classifier: Operating System :: MacOS :: MacOS X
Classifier: Operating System :: Microsoft :: Windows
Classifier: Operating System :: POSIX
Classifier: Operating System :: POSIX :: Linux
Classifier: Programming Language :: Python
Classifier: Programming Language :: Python :: 3
Classifier: Programming Language :: Python :: 3.6
Classifier: Programming Language :: Python :: 3.7
Classifier: Programming Language :: Python :: 3.8
Classifier: Programming Language :: Python :: 3.9
Classifier: Programming Language :: Python :: 3 :: Only
Classifier: Topic :: Software Development :: Libraries :: Python Modules
Provides-Extra: test
Provides-Extra: check
